percent/__init__.py
percent/main.py
percent/percentual_calc.py
percentualCalculation/__init__.py
per_calc-1.1.0.dist-info/LICENSE.txt
per_calc-1.1.0.dist-info/METADATA
per_calc-1.1.0.dist-info/WHEEL
per_calc-1.1.0.dist-info/top_level.txt
per_calc-1.1.0.dist-info/RECORD
