Metadata-Version: 2.1
Name: per-calc
Version: 1.1.0
Summary: <This is a percentual calculator! You're able to calculate the increase of any percentage, as also the decrease of any percentage!>
Home-page: UNKNOWN
Author: <Yanick Francisco
Author-email: <yanickfrancisco24@gmail.com
License: UNKNOWN
Platform: UNKNOWN
Classifier: Programming Language :: Python :: 3
Classifier: License :: OSI Approved :: MIT License
Classifier: Operating System :: OS Independent
License-File: LICENSE.txt
